__init__.py
CustomSession/__init__.py
CustomSession/exceptions.py
CustomSession/identity.py
CustomSession/models.py
CustomSession/sessions/__init__.py
CustomSession/sessions/async_session.py
CustomSession/sessions/sync_session.py
custom_session-1.0.5.dist-info/METADATA
custom_session-1.0.5.dist-info/WHEEL
custom_session-1.0.5.dist-info/licenses/LICENSE
custom_session-1.0.5.dist-info/RECORD
