Metadata-Version: 2.1
Name: custom_session
Version: 1.0.5
Summary: Create HTTP sessions that maintain a unique user-agent, proxy, and handle session specific metadata
Project-URL: Homepage, https://github.com/jakestrouse00/CustomSessions
Author-email: Jake Strouse <jstrouse@meh.llc>
License-File: LICENSE
Classifier: License :: OSI Approved :: MIT License
Classifier: Operating System :: OS Independent
Classifier: Programming Language :: Python :: 3
Requires-Python: >=3.10
Requires-Dist: faker==19.6.1
Requires-Dist: httpx==0.25.0
Requires-Dist: requests==2.31.0
Requires-Dist: ua-generator==0.1.8
